dj_paddle_billing/__about__.py
dj_paddle_billing/__init__.py
dj_paddle_billing-0.0.1.dist-info/METADATA
dj_paddle_billing-0.0.1.dist-info/WHEEL
dj_paddle_billing-0.0.1.dist-info/licenses/LICENSE.txt
dj_paddle_billing-0.0.1.dist-info/RECORD
